torcheval/__init__.py
torcheval/py.typed
torcheval/version.py
torcheval/metrics/__init__.py
torcheval/metrics/metric.py
torcheval/metrics/synclib.py
torcheval/metrics/toolkit.py
torcheval/metrics/aggregation/__init__.py
torcheval/metrics/aggregation/auc.py
torcheval/metrics/aggregation/cat.py
torcheval/metrics/aggregation/max.py
torcheval/metrics/aggregation/mean.py
torcheval/metrics/aggregation/min.py
torcheval/metrics/aggregation/sum.py
torcheval/metrics/aggregation/throughput.py
torcheval/metrics/audio/__init__.py
torcheval/metrics/audio/fad.py
torcheval/metrics/classification/__init__.py
torcheval/metrics/classification/accuracy.py
torcheval/metrics/classification/auprc.py
torcheval/metrics/classification/auroc.py
torcheval/metrics/classification/binary_normalized_entropy.py
torcheval/metrics/classification/binned_auprc.py
torcheval/metrics/classification/binned_auroc.py
torcheval/metrics/classification/binned_precision_recall_curve.py
torcheval/metrics/classification/confusion_matrix.py
torcheval/metrics/classification/f1_score.py
torcheval/metrics/classification/precision.py
torcheval/metrics/classification/precision_recall_curve.py
torcheval/metrics/classification/recall.py
torcheval/metrics/classification/recall_at_fixed_precision.py
torcheval/metrics/functional/__init__.py
torcheval/metrics/functional/tensor_utils.py
torcheval/metrics/functional/aggregation/__init__.py
torcheval/metrics/functional/aggregation/auc.py
torcheval/metrics/functional/aggregation/mean.py
torcheval/metrics/functional/aggregation/sum.py
torcheval/metrics/functional/aggregation/throughput.py
torcheval/metrics/functional/classification/__init__.py
torcheval/metrics/functional/classification/accuracy.py
torcheval/metrics/functional/classification/auprc.py
torcheval/metrics/functional/classification/auroc.py
torcheval/metrics/functional/classification/binary_normalized_entropy.py
torcheval/metrics/functional/classification/binned_auprc.py
torcheval-0.0.7.dist-info/LICENSE
torcheval-0.0.7.dist-info/METADATA
torcheval-0.0.7.dist-info/WHEEL
torcheval-0.0.7.dist-info/top_level.txt
torcheval-0.0.7.dist-info/zip-safe
torcheval-0.0.7.dist-info/RECORD
