Metadata-Version: 2.1
Name: torcheval
Version: 0.0.7
Summary: A library for providing a simple interface to create new metrics and an easy-to-use toolkit for metric computations and checkpointing.
Home-page: https://github.com/pytorch/torcheval
Author: torcheval team
Author-email: yicongd@fb.com
License: BSD-3
Keywords: pytorch,evaluation,metrics
Classifier: Development Status :: 2 - Pre-Alpha
Classifier: Intended Audience :: Developers
Classifier: Intended Audience :: Science/Research
Classifier: License :: OSI Approved :: BSD License
Classifier: Programming Language :: Python :: 3
Classifier: Programming Language :: Python :: 3.7
Classifier: Topic :: Scientific/Engineering :: Artificial Intelligence
Requires-Python: >=3.7
Provides-Extra: dev
Provides-Extra: image
License-File: LICENSE
